cloud_storages/__init__.py
cloud_storages/utils.py
cloud_storages/backends/__init__.py
cloud_storages/backends/appwrite.py
cloud_storages/backends/dropbox.py
django_cloud_storages-1.2.3.dist-info/METADATA
django_cloud_storages-1.2.3.dist-info/WHEEL
django_cloud_storages-1.2.3.dist-info/licenses/LICENSE
django_cloud_storages-1.2.3.dist-info/RECORD
